<Document>

  # Экспедиции по утилизации
  <Box>
    <GuideEntityEmbed Entity="ComputerSalvageExpedition"/>
    <GuideEntityEmbed Entity="TelecomServerFilledShuttle"/>
  </Box>

  Во время экспедиции ваш корабль совершает прыжок на планету, и вы должны выполнить задание за ограниченное время.  
  Когда время истечёт, корабль вернётся назад — [bold]с вами или без вас[/bold].

  Корабли, купленные на форпосте Фронтира, [bold]не могут[/bold] участвовать в экспедициях, но [italic]любой корабль, купленный в [bold]Экспедиционном корпусе[/bold], может[/italic].  
  Для начала используйте [color=#a4885c]консоль утилизации[/color] на борту.

  Чтобы отправиться в экспедицию:
  - Припаркуйте корабль так, чтобы вокруг было по 200 м свободного пространства.
  - Используйте [color=#a4885c]консоль утилизации[/color].
  - Выберите одну из пяти доступных миссий.
  - Обратите внимание на противников, условия, время и цель задания.
  - Пристегнитесь к креслу, чтобы не упасть.

  Советы по экспедициям:
  - Начинайте с лёгких миссий, переходите к сложным по мере подготовки.
  - У разных врагов — разные уязвимости. Подбирайте снаряжение под конкретную угрозу.
  - Если не уверены в победе — не вступайте в бой.

  По прибытии на место вам сообщат направление к цели. Там будет здание — проникните внутрь и выполните задание.  
  Примечание: север — это верх экрана в стандартной ориентации (по умолчанию клавиша: [color=#028ed9][keybind="CameraReset"/][/color]).

  На планете у вас не будет связи с остальным сектором Фронтира. Без установленного [color=#a4885c]телекоммуникационного сервера[/color] даже экипаж экспедиции не сможет общаться по радио.

  # Подготовка
  <Box>
    <GuideEntityEmbed Entity="MobBloodCultistZealotMelee"/>
    <GuideEntityEmbed Entity="MobFleshGolemExpeditions"/>
    <GuideEntityEmbed Entity="MobArgocyteEnforcerExpeditions"/>
    <GuideEntityEmbed Entity="MobCarpHolo"/>
    <GuideEntityEmbed Entity="MobRogueSiliconHunter"/>
  </Box>

  Во время экспедиций вы столкнётесь с опасностями: от агрессивной фауны до культистов или автоматонов.  
  Чтобы выжить и вернуться с добычей, нужно быть готовым: иметь снаряжение, знать его применение и доверять команде.

  # Снаряжение

  ## Опасности окружающей среды

  Первая угроза — [italic]сама планета[/italic].  
  Атмосфера и температура могут быть опасными.  
  В разделе [color=#a4885c]Модификаторы[/color] консоли утилизации указывается обстановка.

  <Box>
    <GuideEntityEmbed Entity="FloorLiquidPlasmaEntity"/>
    <GuideEntityEmbed Entity="FloorLavaEntity"/>
  </Box>
  [bold][color=#a4885c]Биомы:[/color][/bold]
  - [bold]Луга/Пещеры/Тень:[/bold] угроз не зафиксировано.
  - [bold]Снег:[/bold] возможны лужи жидкой плазмы. При контакте возникает возгорание.
  - [bold]Лава:[/bold] возможны лавовые озёра. При контакте возникает возгорание.

  Если вы всё же загорелись — [bold]нажмите на [color=#ee0000]иконку огня[/color][/bold], чтобы упасть и кататься по земле. Может потребоваться [bold]несколько попыток[/bold], чтобы потушиться.

  <Box>
    <GuideEntityEmbed Entity="ClothingMaskGas"/>
    <GuideEntityEmbed Entity="AirTankFilled"/>
  </Box>
  [bold][color=#a4885c]Атмосферные модификаторы:[/color][/bold]
  - [bold]Отсутствуют:[/bold] можно дышать без интерналов.
  - [bold]Опасная атмосфера:[/bold] токсичная или разрежённая — нужны интерналы, в тяжёлых случаях — EVA или скафандр.
  - [bold]Взрывоопасная атмосфера:[/bold] содержит газообразную плазму. Возможны возгорания всей планеты.

  <Box>
    <GuideEntityEmbed Entity="ClothingOuterWinterMiner"/>
    <GuideEntityEmbed Entity="ClothingOuterHardsuitEVA"/>
    <GuideEntityEmbed Entity="ClothingOuterHardsuitBasic"/>
  </Box>
  [bold][color=#a4885c]Температурные модификаторы:[/color][/bold]
  - [bold]Нет:[/bold] тепло, спецодежда не требуется.
  - [bold]Низкая температура:[/bold] холодно, но терпимо. Рептилиям лучше надеть зимнее пальто или скафандр.
  - [bold]Экстремальный холод:[/bold] близко к абсолютному нулю — обязателен скафандр.
  - [bold]Высокая температура:[/bold] ≈150°C. Требуется термозащита или скафандр.
  - [bold]Экстремальный жар:[/bold] очень высокая температура — обязателен скафандр.

  <Box>
    <GuideEntityEmbed Entity="Flare"/>
    <GuideEntityEmbed Entity="GlowstickBlue"/>
    <GuideEntityEmbed Entity="FlashlightLantern"/>
    <GuideEntityEmbed Entity="Floodlight"/>
  </Box>
  [bold][color=#a4885c]Время суток:[/color][/bold]
  - [bold]Утро/День/Вечер:[/bold] достаточно естественного света.
  - [bold]Ночь:[/bold] кромешная тьма — требуются источники света.

  [bold][color=#a4885c]Ограничения по времени:[/color][/bold]
  - [bold]Спешка:[/bold] меньше времени на выполнение миссии. Не перегружайтесь тяжёлым снаряжением.

  ## Инструменты
  <Box>
    <GuideEntityEmbed Entity="Pickaxe"/>
    <GuideEntityEmbed Entity="Crowbar"/>
    <GuideEntityEmbed Entity="Wrench"/>
    <GuideEntityEmbed Entity="Screwdriver"/>
    <GuideEntityEmbed Entity="Wirecutter"/>
  </Box>
  <Box>
    <GuideEntityEmbed Entity="ClothingEyesGlassesMeson"/>
    <GuideEntityEmbed Entity="Welder"/>
    <GuideEntityEmbed Entity="Multitool"/>
    <GuideEntityEmbed Entity="RadioHandheld"/>
  </Box>
  Утилизация часто требует прорываться через каменные слои, вскрывать стены и окна заброшенных объектов. Вам может понадобиться взломать разгерметизированные шлюзы или разобрать ценное оборудование.

  Инструменты облегчают задачи:
  - Лом — быстро открывает шлюзы.
  - Дрель — позволяет прокапывать скалы.
  - Рация — заменяет стационарную радиосвязь в отсутствие телекоммуникационного сервера.

  Подробнее см. разделы [textlink="Инженерия" link="Engineering"] и [textlink="Строительство" link="Construction"].

  ## Медицина
  <Box>
    <GuideEntityEmbed Entity="EmergencyMedipen"/>
    <GuideEntityEmbed Entity="Brutepack"/>
    <GuideEntityEmbed Entity="Ointment"/>
    <GuideEntityEmbed Entity="Gauze"/>
  </Box>
  <Box>
    <GuideEntityEmbed Entity="MedicatedSuture"/>
    <GuideEntityEmbed Entity="RegenerativeMesh"/>
    <GuideEntityEmbed Entity="Tourniquet"/>
  </Box>
  Вы получите урон. Это неизбежно. Знание базовой медицины и наличие средств первой помощи может спасти вам или товарищу жизнь.

  Перед вылетом приобретите медикаменты для лечения [color=red]тупых[/color] и [color=#ffa500]ожоговых[/color] повреждений, а также для остановки [color=red]кровотечения[/color], например [color=#a4885c]марлю[/color] или [color=#a4885c]эпинефрин[/color].

  Простые лекарства можно купить в автоматах. Эффективные препараты доступны у медиков и игроков, оказывающих медуслуги.

  Помните: наличие аптечки — лишь полдела. Остальное — [textlink="изучите в разделе медицины" link="Medical Doctor"].

  ## Броня
  <Box>
    <GuideEntityEmbed Entity="ClothingHeadHelmetBasic"/>
    <GuideEntityEmbed Entity="ClothingOuterArmorBulletproof"/>
    <GuideEntityEmbed Entity="ClothingOuterArmorReflective"/>
    <GuideEntityEmbed Entity="RiotShield"/>
  </Box>
  Урон не всегда можно избежать. Ношение брони снижает получаемый урон и увеличивает шанс выживания.

  Подбирайте защиту под врага:
  - [textlink="Силы Синдиката" link="MobsExpeditionGuideSyndicate"] используют огнестрел ([color=yellow]колющий[/color] урон) — пригодится пуленепробиваемый жилет.
  - [textlink="Силиконы" link="MobsExpeditionGuideSilicons"] наносят [color=#ffa500]тепловой[/color] урон — используйте отражающий жилет.

  ## Командная работа
  <Box>
    <GuideEntityEmbed Entity="GuidebookMemeNpcGood" Caption="добрый,"/>
    <GuideEntityEmbed Entity="GuidebookMemeNpcBad" Caption="плохой,"/>
    <GuideEntityEmbed Entity="GuidebookMemeNpcUgly" Caption="злой"/>
    <GuideEntityEmbed Entity="GuidebookMemeNpcThatGuy" Caption="и вот тот тип"/>
  </Box>
  Ваша главная опора на экспедиции — товарищи по экипажу. Даже если вы [italic]умеете[/italic] лечиться, вы [italic]не сможете[/italic] этого сделать в бессознательном состоянии.

  <Box>
    <GuideEntityEmbed Entity="TelecomServerFilledShuttle"/>
    <GuideEntityEmbed Entity="EncryptionKeyCommon"/>
  </Box>
  <Box>
    <GuideEntityEmbed Entity="ClothingHeadsetGrey" Caption="гарнитура"/>
    <GuideEntityEmbed Entity="EncryptionKeyMedical"/>
    <GuideEntityEmbed Entity="MedicalTrackingImplanter"/>
  </Box>

  Связь — ключ к выживанию.  
  Используйте гарнитуры с установленными [color=#a4885c]ключами шифрования[/color] и подключённым [color=#a4885c]телекоммуникационным сервером[/color], либо [color=#a4885c]портативные рации[/color] (убедитесь, что они включены!).

  Наличие [color=#a4885c]медицинского ключа шифрования[/color] в вашей гарнитуре позволит вам узнать, если кто-то с [color=#a4885c]имплантом медицинского отслеживания[/color] упадёт в бою.  
  Никого не оставляйте!

  ## Знай врага
  <Box>
    <GuideEntityEmbed Entity="ClothingEyesHudMedical"/>
    <GuideEntityEmbed Entity="ClothingEyesHudDiagnostic"/>
  </Box>

  Адаптация — залог успеха: то, что работает против [textlink="ксеносов" link="MobsExpeditionGuideXenos"], может быть бесполезно против [textlink="наёмников" link="MobsExpeditionGuideMercenaries"].

  Руководство содержит сведения о противниках, но [italic]не заменяет личного опыта[/italic].  
  Спускайтесь на планету, собирайте ресурсы и сражайтесь с опасностями лицом к лицу.  
  Сокровища не будут ждать вечно!

</Document>

